ez_sendgrid/__init__.py
ez_sendgrid/cmd.py
ez_sendgrid/uploader.py
ez_sendgrid-1.1.0.dist-info/entry_points.txt
ez_sendgrid-1.1.0.dist-info/WHEEL
ez_sendgrid-1.1.0.dist-info/METADATA
ez_sendgrid-1.1.0.dist-info/RECORD
