Metadata-Version: 2.1
Name: ez-sendgrid
Version: 1.1.0
Summary: Manage your SendGrid templates easy.
Author: Alex Khaerov
Author-email: i@hayorov.ru
Requires-Python: >=3.5,<4.0
Classifier: Programming Language :: Python :: 3
Classifier: Programming Language :: Python :: 3.5
Classifier: Programming Language :: Python :: 3.6
Classifier: Programming Language :: Python :: 3.7
Classifier: Programming Language :: Python :: 3.8
Requires-Dist: fire (>=0.2.1,<0.3.0)
Requires-Dist: python-decouple (>=3.1,<4.0)
Requires-Dist: pyyaml (>=5.1.2,<6.0.0)
Requires-Dist: sendgrid (>=6.0.5,<7.0.0)
